awesome_git_mosaic/__init__.py
awesome_git_mosaic/__main__.py
awesome_git_mosaic/adapters/__init__.py
awesome_git_mosaic/adapters/console/__init__.py
awesome_git_mosaic/adapters/console/console_adapter.py
awesome_git_mosaic/adapters/git_mosaic/__init__.py
awesome_git_mosaic/adapters/git_mosaic/git_mosaic_adapter.py
awesome_git_mosaic/charmaps/__init__.py
awesome_git_mosaic/charmaps/basic/__init__.py
awesome_git_mosaic/charmaps/basic/basic_charmap.py
awesome_git_mosaic/charmaps/basic/char_model.txt
awesome_git_mosaic/charmaps/charmap.py
awesome_git_mosaic/gateways/__init__.py
awesome_git_mosaic/gateways/git/__init__.py
awesome_git_mosaic/gateways/git/git_gateway.py
awesome_git_mosaic/usecases/__init__.py
awesome_git_mosaic/usecases/make_commit.py
awesome_git_mosaic/usecases/modify_file.py
awesome_git_mosaic/usecases/write_in_console.py
awesome_git_mosaic/usecases/write_mosaic.py
awesome_git_mosaic-0.1.1.dist-info/LICENSE
awesome_git_mosaic-0.1.1.dist-info/METADATA
awesome_git_mosaic-0.1.1.dist-info/WHEEL
awesome_git_mosaic-0.1.1.dist-info/RECORD
